somebar-0.0.8.data/scripts/somebar
somebar_icons/__init__.py
somebar_icons/black@2x.png
somebar_icons/black_alt@2x.png
somebar_icons/blue@2x.png
somebar_icons/cyan@2x.png
somebar_icons/exclamation@2x.png
somebar_icons/green@2x.png
somebar_icons/orange@2x.png
somebar_icons/purple@2x.png
somebar_icons/question@2x.png
somebar_icons/question_alt@2x.png
somebar_icons/red@2x.png
somebar_icons/white@2x.png
somebar_icons/white_alt@2x.png
somebar_icons/yellow@2x.png
tmp/build-env-k63ygz4u/share/applications/somebar.desktop
tmp/build-env-k63ygz4u/share/pixmaps/somebar.xpm
somebar-0.0.8.dist-info/LICENSE
somebar-0.0.8.dist-info/METADATA
somebar-0.0.8.dist-info/WHEEL
somebar-0.0.8.dist-info/top_level.txt
somebar-0.0.8.dist-info/RECORD
