Metadata-Version: 2.1
Name: somebar
Version: 0.0.8
Summary: Simple taskbar widget that displays color dot or custom icon
Home-page: https://github.com/limpbrains/somebar
Author: Ivan
Author-email: ivan.vershigora@gmail.com
License: MIT License
Download-URL: https://github.com/limpbrains/somebar/tarball/0.0.8
Keywords: AnyBar,somebar,taskbar,indicator
Platform: UNKNOWN
Classifier: Programming Language :: Python
Classifier: Programming Language :: Python :: 3
Classifier: Development Status :: 4 - Beta
Classifier: Intended Audience :: Developers
Classifier: Operating System :: POSIX :: Linux
